Up Down Counter/updowncounter.v
module up_down_counter(clk,reset,switch,count);
    input clk, reset, switch;
    output reg [15:0] count;

    always @(posedge clk or posedge reset)
    begin
        if (reset)
            count <= 16'b0;
        else if (switch)
            count <= count + 1;
        else
            count <= count - 1;
    end
endmodule

Project-3-Up-Down_counter/updowncounter_testbench.v
module up_down_counter_tb();
    reg clk, reset, switch;
    wire [15:0] count;

    up_down_counter udp(.clk(clk), .reset(reset), .switch(switch), .count(count));

    initial begin
        $dumpfile("up_down_counter_tb.vcd");
        $dumpvars(0, up_down_counter_tb);

        $monitor("time=%0t | reset=%b | switch=%b | count=%d", $time, reset, switch, count);

        clk = 0;
        reset = 1;
        switch = 0;
       
        #10;
        reset = 0;
      
        switch = 1;
        #160;
  
        switch = 0;
        #160;
      
        reset = 1;
        #10;
        reset = 0;

        $finish;
    end
    always #5 clk = ~clk;
endmodule

Project-3-Up-Down_counter/up_down_counter_tb.vcd
$date
	Fri Sep 11 19:27:47 2026
$end
$version
	Icarus Verilog
$end
$timescale
	1s
$end
$scope module up_down_counter_tb $end
$var wire 16 ! count [15:0] $end
$var reg 1 " clk $end
$var reg 1 # reset $end
$var reg 1 $ switch $end
$scope module udp $end
$var wire 1 " clk $end
$var wire 1 # reset $end
$var wire 1 $ switch $end
$var reg 16 % count [15:0] $end
$upscope $end
$upscope $end
$enddefinitions $end
$comment Show the parameter values. $end
$dumpall
$end
#0
$dumpvars
b0 %
0$
1#
0"
b0 !
$end
#5
1"
#10
0"
1$
0#
#15
b1 !
b1 %
1"
#20
0"
#25
b10 !
b10 %
1"
#30
0"
#35
b11 !
b11 %
1"
#40
0"
#45
b100 !
b100 %
1"
#50
0"
#55
b101 !
b101 %
1"
#60
0"
#65
b110 !
b110 %
1"
#70
0"
#75
b111 !
b111 %
1"
#80
0"
#85
b1000 !
b1000 %
1"
#90
0"
#95
b1001 !
b1001 %
1"
#100
0"
#105
b1010 !
b1010 %
1"
#110
0"
#115
b1011 !
b1011 %
1"
#120
0"
#125
b1100 !
b1100 %
1"
#130
0"
#135
b1101 !
b1101 %
1"
#140
0"
#145
b1110 !
b1110 %
1"
#150
0"
#155
b1111 !
b1111 %
1"
#160
0"
#165
b10000 !
b10000 %
1"
#170
0"
0$
#175
b1111 !
b1111 %
1"
#180
0"
#185
b1110 !
b1110 %
1"
#190
0"
#195
b1101 !
b1101 %
1"
#200
0"
#205
b1100 !
b1100 %
1"
#210
0"
#215
b1011 !
b1011 %
1"
#220
0"
#225
b1010 !
b1010 %
1"
#230
0"
#235
b1001 !
b1001 %
1"
#240
0"
#245
b1000 !
b1000 %
1"
#250
0"
#255
b111 !
b111 %
1"
#260
0"
#265
b110 !
b110 %
1"
#270
0"
#275
b101 !
b101 %
1"
#280
0"
#285
b100 !
b100 %
1"
#290
0"
#295
b11 !
b11 %
1"
#300
0"
#305
b10 !
b10 %
1"
#310
0"
#315
b1 !
b1 %
1"
#320
0"
#325
b0 !
b0 %
1"
#330
0"
1#
#335
1"
#340
0"
0#
