Project-2-Special_MUX_8:1/smux81.v
module smux81(a,b,c,d,e,f,g,h,sel,y);
    input a,b,c,d,e,f,g,h;
    input [2:0] sel;
    output y;
    assign y=(~sel[2]&~sel[1]&~sel[0])?a:
             (~sel[2]&~sel[1]&sel[0])?b:
             (~sel[2]&sel[1]&~sel[0])?c:
             (~sel[2]&sel[1]&sel[0])?d:
             (sel[2]&~sel[1]&~sel[0])?~e:
             (sel[2]&~sel[1]&sel[0])?~f:
             (sel[2]&sel[1]&~sel[0])?~g:~h;
endmodule

Project-2-Special_MUX_8:1/smux81_testebench.v
module smux81_tb;
    reg a,b,c,d,e,f,g,h;
    reg [2:0] sel;
    wire y;
    smux81 smx(.a(a),.b(b),.c(c),.d(d),.e(e),.f(f),.g(g),.h(h),.sel(sel),.y(y));
    initial begin
        $dumpfile("smux81_tb.vcd");
        $dumpvars(0, smux81_tb);

        $monitor("time=%0t,a=%b,b=%b,c=%b,d=%b,e=%b,f=%b,g=%b,h=%b,sel=%b,y=%b", $time,a,b,c,d,e,f,g,h,sel,y);
        a=0;b=0;c=0;d=0;e=0;f=0;g=0;h=0;sel=3'b000;
        #5 a=1;b=1;c=1;d=1;e=1;f=1;g=1;h=1;sel=3'b000;
        #5 sel=3'b001;
        #5 sel=3'b010;
        #5 sel=3'b011;
        #5 sel=3'b100;
        #5 sel=3'b101;
        #5 sel=3'b110;
        #5 sel=3'b111;
        #10 $finish;
    end
endmodule

Project-2-Special_MUX_8:1/smux81_tb.vcd
$date
	Fri Sep 11 20:09:43 2026
$end
$version
	Icarus Verilog
$end
$timescale
	1s
$end
$scope module smux81_tb $end
$var wire 1 ! y $end
$var reg 1 " a $end
$var reg 1 # b $end
$var reg 1 $ c $end
$var reg 1 % d $end
$var reg 1 & e $end
$var reg 1 ' f $end
$var reg 1 ( g $end
$var reg 1 ) h $end
$var reg 3 * sel [2:0] $end
$scope module smx $end
$var wire 1 " a $end
$var wire 1 # b $end
$var wire 1 $ c $end
$var wire 1 % d $end
$var wire 1 & e $end
$var wire 1 ' f $end
$var wire 1 ( g $end
$var wire 1 ) h $end
$var wire 3 + sel [2:0] $end
$var wire 1 ! y $end
$upscope $end
$upscope $end
$enddefinitions $end
$comment Show the parameter values. $end
$dumpall
$end
#0
$dumpvars
b0 +
b0 *
0)
0(
0'
0&
0%
0$
0#
0"
0!
$end
#5
1!
1)
1(
1'
1&
1%
1$
1#
1"
#10
b1 *
b1 +
#15
b10 *
b10 +
#20
b11 *
b11 +
#25
0!
b100 *
b100 +
#30
b101 *
b101 +
#35
b110 *
b110 +
#40
b111 *
b111 +
