Project-4-Full_Adder/fulladder.v
module fa(a,b,c,cout,s);
    input a,b,c;
    output cout,s;
    assign s=a^b^c;
    assign cout=(a&b)|(b&c)|(c&a);
endmodule

Project-4-Full_Adder/fulladder_testbench.v
module fa_tb;
    reg a,b,c;
    wire cout,s;
    fa FA(.a(a), .b(b), .c(c), .cout(cout), .s(s));

    initial begin
            $dumpfile("fa_tb.vcd");
            $dumpvars(0, fa_tb);
            $monitor("time=%0t, a=%b, b=%b, c=%b, cout=%b, s=%b", $time, a, b, c, cout, s);
            a=0;b=0;c=0;
            #5 a=0;b=0;c=1;
            #5 a=0;b=1;c=0;
            #5 a=0;b=1;c=1;
            #5 a=1;b=0;c=0;
            #5 a=1;b=0;c=1;
            #5 a=1;b=1;c=0;
            #5 a=1;b=1;c=1;
            #5 $finish;

        end
endmodule

Project-4-Full_Adder/fa_tb.vcd
$date
	Tue Sep 15 12:11:47 2026
$end
$version
	Icarus Verilog
$end
$timescale
	1s
$end
$scope module fa_tb $end
$var wire 1 ! s $end
$var wire 1 " cout $end
$var reg 1 # a $end
$var reg 1 $ b $end
$var reg 1 % c $end
$scope module FA $end
$var wire 1 # a $end
$var wire 1 $ b $end
$var wire 1 % c $end
$var wire 1 " cout $end
$var wire 1 ! s $end
$upscope $end
$upscope $end
$enddefinitions $end
$comment Show the parameter values. $end
$dumpall
$end
#0
$dumpvars
0%
0$
0#
0"
0!
$end
#5
1!
1%
#10
0%
1$
#15
1"
0!
1%
#20
0"
1!
0%
0$
1#
#25
1"
0!
1%
#30
0%
1$
#35
1!
1%
